roc_svchost/__init__.py
roc_svchost/factories/__init__.py
roc_svchost/factories/config_factory.py
roc_svchost/factories/message_adapter_factory.py
roc_svchost/factories/service_processor_factory.py
roc_svchost/logger.py
roc_svchost/process.py
roc_svchost/services/__init__.py
roc_svchost/services/processor.py
roc_svchost/utils.py
roc_svchost/version.py
roc_svchost-0.1.16.dist-info/METADATA
roc_svchost-0.1.16.dist-info/WHEEL
roc_svchost-0.1.16.dist-info/entry_points.txt
roc_svchost-0.1.16.dist-info/RECORD
