Metadata-Version: 2.1
Name: roc_svchost
Version: 0.1.16
Summary: 
Author: Matias Garafoni
Author-email: matias.garafoni@gmail.com
Requires-Python: >=3.10,<4.0
Classifier: Programming Language :: Python :: 3
Classifier: Programming Language :: Python :: 3.10
Classifier: Programming Language :: Python :: 3.11
Classifier: Programming Language :: Python :: 3.12
Requires-Dist: pytest (>=7.4.3,<8.0.0)
Requires-Dist: rococo (==1.0.*)
Requires-Dist: schedule (>=1.2.1,<2.0.0)
